<record netinfo="no_ssid_wifi" time="1522387049">
    <item ip="183.3.224.146" port="8080" historyresult="1"/>
    <item ip="183.3.234.100" port="80" historyresult="0"/>
    <item ip="14.215.158.101" port="80" historyresult="0"/>
    <item ip="183.3.234.105" port="80" historyresult="0"/>
    <item ip="14.215.158.100" port="80" historyresult="0"/>
    <item ip="113.96.209.101" port="80" historyresult="0"/>
    <item ip="14.17.42.45" port="80" historyresult="0"/>
    <item ip="113.96.202.100" port="80" historyresult="0"/>
    <item ip="183.61.46.199" port="80" historyresult="0"/>
    <item ip="183.3.224.146" port="80" historyresult="1"/>
    <item ip="113.96.209.100" port="80" historyresult="0"/>
</record>
